cm_time/__init__.py
cm_time/main.py
cm_time/py.typed
cm_time-0.1.2.dist-info/LICENSE
cm_time-0.1.2.dist-info/METADATA
cm_time-0.1.2.dist-info/WHEEL
cm_time-0.1.2.dist-info/RECORD
