Metadata-Version: 2.1
Name: cm-time
Version: 0.1.2
Summary: A simple context manager that measures time using perf_counter()
Home-page: https://github.com/34j/cm-time
License: CC0-1.0
Author: 34j
Author-email: 34j.95a2p@simplelogin.com
Requires-Python: >=3.7,<4.0
Classifier: Development Status :: 2 - Pre-Alpha
Classifier: Intended Audience :: Developers
Classifier: License :: CC0 1.0 Universal (CC0 1.0) Public Domain Dedication
Classifier: Natural Language :: English
Classifier: Operating System :: OS Independent
Classifier: Programming Language :: Python :: 3
Classifier: Programming Language :: Python :: 3.7
Classifier: Programming Language :: Python :: 3.8
Classifier: Programming Language :: Python :: 3.9
Classifier: Programming Language :: Python :: 3.10
Classifier: Programming Language :: Python :: 3.11
Classifier: Topic :: Software Development :: Libraries
Requires-Dist: typing-extensions (>=4.4.0,<5.0.0) ; python_version < "3.10"
Project-URL: Bug Tracker, https://github.com/34j/cm-time/issues
Project-URL: Changelog, https://github.com/34j/cm-time/blob/main/CHANGELOG.md
Project-URL: Documentation, https://cm-time.readthedocs.io
Project-URL: Repository, https://github.com/34j/cm-time
